tcat/__init__.py
tcat/factory/__init__.py
tcat/factory/datasetFactory.py
tcat/models/__init__.py
tcat/models/dataset.py
tcat/models/dictionary.py
tcat/models/document.py
tcat/models/group.py
tcat/models/test.py
tcat/models/weightedDictionary.py
tcat/models/word.py
tcat/models/wordVector.py
text-categorization/__init__.py
text-categorization/dataloss.py
text-categorization/importing.py
text-categorization/log.py
text-categorization/main.py
text-categorization/result.py
text-categorization/saving.py
text-categorization/setting.py
text_categorization/__init__.py
text_categorization/dataloss.py
text_categorization/datasetFactory.py
text_categorization/importing.py
text_categorization/log.py
text_categorization/main.py
text_categorization/result.py
text_categorization/saving.py
text_categorization/setting.py
text_categorization/factory/__init__.py
text_categorization/factory/datasetFactory.py
text_categorization/models/__init__.py
text_categorization/models/dataset.py
text_categorization/models/dictionary.py
text_categorization/models/document.py
text_categorization/models/group.py
text_categorization/models/test.py
text_categorization/models/weightedDictionary.py
text_categorization/models/word.py
text_categorization/models/wordVector.py
tcat-0.1.2.dist-info/License.txt
tcat-0.1.2.dist-info/METADATA
tcat-0.1.2.dist-info/WHEEL
tcat-0.1.2.dist-info/top_level.txt
tcat-0.1.2.dist-info/RECORD
