Metadata-Version: 2.1
Name: tcat
Version: 0.1.2
Summary: Package for machine learning with naive bayes classifier
Home-page: https://github.com/kinqert/text-categorization
Author: Lorenzo Adreani
Author-email: adreanilorenzo@outlook.it
License: UNKNOWN
Platform: UNKNOWN
Classifier: Programming Language :: Python :: 3
Classifier: License :: OSI Approved :: MIT License
Classifier: Operating System :: OS Independent
Requires-Python: >=3.7
License-File: License.txt
Requires-Dist: Sklearn
